setup.py
Gwilio/Gwilio.py
Gwilio/__init__.py
Gwilio.egg-info/PKG-INFO
Gwilio.egg-info/SOURCES.txt
Gwilio.egg-info/dependency_links.txt
Gwilio.egg-info/top_level.txt