Metadata-Version: 1.0
Name: Gwilio
Version: 1.1
Summary: Host your own Twilio clone for free
Home-page: https://github.com/robertf224/Gwilio/
Author: Robert Fidler
Author-email: robertf224@gmail.com
License: UNKNOWN
Keywords: Twilio,Gwilio,SMS
Platform: UNKNOWN
